{
    "total_time": "3,308 hrs 30 mins",
    "updated": true,
    "elo": 3309,
    "languages": [
        {
            "language": "Bash",
            "time": "35 hrs 26 mins"
        },
        {
            "language": "C",
            "time": "225 hrs 28 mins"
        },
        {
            "language": "CSS",
            "time": "151 hrs 3 mins"
        },
        {
            "language": "EJS",
            "time": "258 hrs 49 mins"
        },
        {
            "language": "Go",
            "time": "152 hrs 38 mins"
        },
        {
            "language": "HTML",
            "time": "37 hrs 18 mins"
        },
        {
            "language": "JSON",
            "time": "14 hrs 2 mins"
        },
        {
            "language": "JavaScript",
            "time": "1,330 hrs 34 mins"
        },
        {
            "language": "Markdown",
            "time": "9 hrs 51 mins"
        },
        {
            "language": "PHP",
            "time": "597 hrs 5 mins"
        },
        {
            "language": "Python",
            "time": "2 hrs 40 mins"
        },
        {
            "language": "SQL",
            "time": "2 hrs 40 mins"
        },
        {
            "language": "Smarty",
            "time": "431 hrs 42 mins"
        },
        {
            "language": "Text",
            "time": "3 hrs 13 mins"
        },
        {
            "language": "Twig",
            "time": "7 hrs 4 mins"
        },
        {
            "language": "TypeScript",
            "time": "41 hrs 13 mins"
        },
        {
            "language": "XML",
            "time": "3 hrs 37 mins"
        },
        {
            "language": "YAML",
            "time": "4 hrs 7 mins"
        }
    ]
}