{
    "total_time": "8,215 hrs 29 mins",
    "updated": true,
    "elo": 8216,
    "languages": [
        {
            "language": "AI Assistant",
            "time": "107 hrs 52 mins"
        },
        {
            "language": "Astro",
            "time": "6 hrs 41 mins"
        },
        {
            "language": "Bash",
            "time": "156 hrs 14 mins"
        },
        {
            "language": "C#",
            "time": "15 hrs 15 mins"
        },
        {
            "language": "C++",
            "time": "141 hrs 40 mins"
        },
        {
            "language": "CSS",
            "time": "23 hrs 4 mins"
        },
        {
            "language": "CSV",
            "time": "4 hrs 52 mins"
        },
        {
            "language": "Docker",
            "time": "35 hrs 15 mins"
        },
        {
            "language": "Git Config",
            "time": "7 hrs 48 mins"
        },
        {
            "language": "GraphQL",
            "time": "37 hrs 7 mins"
        },
        {
            "language": "HTML",
            "time": "78 hrs 8 mins"
        },
        {
            "language": "JSON",
            "time": "359 hrs 2 mins"
        },
        {
            "language": "Java",
            "time": "5 hrs 56 mins"
        },
        {
            "language": "JavaScript",
            "time": "117 hrs 13 mins"
        },
        {
            "language": "Liquid",
            "time": "17 hrs 45 mins"
        },
        {
            "language": "Lua",
            "time": "3 hrs 15 mins"
        },
        {
            "language": "Markdown",
            "time": "85 hrs 26 mins"
        },
        {
            "language": "Prisma",
            "time": "7 hrs 46 mins"
        },
        {
            "language": "Python",
            "time": "52 hrs 1 min"
        },
        {
            "language": "Rust",
            "time": "118 hrs 49 mins"
        },
        {
            "language": "SCSS",
            "time": "135 hrs 24 mins"
        },
        {
            "language": "SQL",
            "time": "5 hrs 7 mins"
        },
        {
            "language": "TOML",
            "time": "15 hrs 56 mins"
        },
        {
            "language": "TSConfig",
            "time": "23 hrs 12 mins"
        },
        {
            "language": "Text",
            "time": "3 hrs 1 min"
        },
        {
            "language": "TypeScript",
            "time": "6,443 hrs 39 mins"
        },
        {
            "language": "Vue.js",
            "time": "38 hrs 41 mins"
        },
        {
            "language": "XML",
            "time": "5 hrs 24 mins"
        },
        {
            "language": "YAML",
            "time": "163 hrs 56 mins"
        }
    ]
}