{
    "total_time": "7,499 hrs 17 mins",
    "updated": true,
    "elo": 7500,
    "languages": [
        {
            "language": "Assembly",
            "time": "4 hrs 6 mins"
        },
        {
            "language": "Bash",
            "time": "73 hrs 39 mins"
        },
        {
            "language": "CSS",
            "time": "49 hrs 14 mins"
        },
        {
            "language": "CSV",
            "time": "26 hrs 46 mins"
        },
        {
            "language": "Cocoa",
            "time": "8 hrs 33 mins"
        },
        {
            "language": "CocoaPods",
            "time": "17 hrs 14 mins"
        },
        {
            "language": "Dart",
            "time": "4,367 hrs 1 min"
        },
        {
            "language": "Docker",
            "time": "4 hrs 30 mins"
        },
        {
            "language": "Elixir",
            "time": "139 hrs 7 mins"
        },
        {
            "language": "Ezhil",
            "time": "4 hrs 19 mins"
        },
        {
            "language": "Git Config",
            "time": "25 hrs 7 mins"
        },
        {
            "language": "Gradle",
            "time": "4 hrs 42 mins"
        },
        {
            "language": "Groovy",
            "time": "67 hrs 9 mins"
        },
        {
            "language": "HTML",
            "time": "44 hrs 8 mins"
        },
        {
            "language": "INI",
            "time": "8 hrs 18 mins"
        },
        {
            "language": "Image (svg)",
            "time": "13 hrs 16 mins"
        },
        {
            "language": "Java",
            "time": "20 hrs 37 mins"
        },
        {
            "language": "Java Properties",
            "time": "6 hrs 22 mins"
        },
        {
            "language": "JavaScript",
            "time": "12 hrs 40 mins"
        },
        {
            "language": "Kotlin",
            "time": "94 hrs 54 mins"
        },
        {
            "language": "Markdown",
            "time": "353 hrs 46 mins"
        },
        {
            "language": "Objective-C",
            "time": "18 hrs 23 mins"
        },
        {
            "language": "Objective-C++",
            "time": "17 hrs 12 mins"
        },
        {
            "language": "Perl",
            "time": "2 hrs 36 mins"
        },
        {
            "language": "Properties",
            "time": "8 hrs 48 mins"
        },
        {
            "language": "Python",
            "time": "20 hrs 16 mins"
        },
        {
            "language": "Ruby",
            "time": "6 hrs 55 mins"
        },
        {
            "language": "SQL",
            "time": "51 hrs 50 mins"
        },
        {
            "language": "Svelte",
            "time": "4 hrs 34 mins"
        },
        {
            "language": "Swift",
            "time": "17 hrs 28 mins"
        },
        {
            "language": "TOML",
            "time": "4 hrs 52 mins"
        },
        {
            "language": "TSQL",
            "time": "4 hrs 33 mins"
        },
        {
            "language": "Text",
            "time": "30 hrs 15 mins"
        },
        {
            "language": "TypeScript",
            "time": "1,615 hrs 24 mins"
        },
        {
            "language": "XML",
            "time": "92 hrs 40 mins"
        },
        {
            "language": "YAML",
            "time": "258 hrs 3 mins"
        }
    ]
}