{
    "total_time": "1,246 hrs 11 mins",
    "updated": true,
    "elo": 1247,
    "languages": [
        {
            "language": "Bash",
            "time": "3 hrs 13 mins"
        },
        {
            "language": "Binary",
            "time": "6 hrs 11 mins"
        },
        {
            "language": "C",
            "time": "12 hrs 27 mins"
        },
        {
            "language": "C#",
            "time": "9 hrs 16 mins"
        },
        {
            "language": "C++",
            "time": "793 hrs 35 mins"
        },
        {
            "language": "C/C",
            "time": "78 hrs 48 mins"
        },
        {
            "language": "Go",
            "time": "157 hrs 11 mins"
        },
        {
            "language": "INI",
            "time": "3 hrs 42 mins"
        },
        {
            "language": "JSON",
            "time": "20 hrs 8 mins"
        },
        {
            "language": "JavaScript",
            "time": "5 hrs 50 mins"
        },
        {
            "language": "Objective-C",
            "time": "47 hrs"
        },
        {
            "language": "Rust",
            "time": "13 hrs 38 mins"
        },
        {
            "language": "TypeScript",
            "time": "95 hrs 12 mins"
        }
    ]
}