{
    "total_time": "3,092 hrs 11 mins",
    "updated": true,
    "elo": 3093,
    "languages": [
        {
            "language": "Bash",
            "time": "31 hrs 16 mins"
        },
        {
            "language": "CSS",
            "time": "20 hrs 47 mins"
        },
        {
            "language": "CSV",
            "time": "14 hrs 49 mins"
        },
        {
            "language": "Git Config",
            "time": "3 hrs 59 mins"
        },
        {
            "language": "HTML",
            "time": "9 hrs 44 mins"
        },
        {
            "language": "JSON",
            "time": "63 hrs 2 mins"
        },
        {
            "language": "JavaScript",
            "time": "59 hrs 31 mins"
        },
        {
            "language": "Markdown",
            "time": "21 hrs 50 mins"
        },
        {
            "language": "Python",
            "time": "2,787 hrs 7 mins"
        },
        {
            "language": "SSH Config",
            "time": "2 hrs 51 mins"
        },
        {
            "language": "TOML",
            "time": "31 hrs 4 mins"
        },
        {
            "language": "Text",
            "time": "8 hrs 42 mins"
        },
        {
            "language": "TypeScript",
            "time": "14 hrs 32 mins"
        },
        {
            "language": "YAML",
            "time": "22 hrs 57 mins"
        }
    ]
}