{
    "total_time": "5,647 hrs 11 mins",
    "updated": true,
    "elo": 5648,
    "languages": [
        {
            "language": "Bash",
            "time": "23 hrs 46 mins"
        },
        {
            "language": "Batchfile",
            "time": "5 hrs 48 mins"
        },
        {
            "language": "Binary",
            "time": "12 hrs 52 mins"
        },
        {
            "language": "C#",
            "time": "239 hrs 50 mins"
        },
        {
            "language": "CSHTML",
            "time": "213 hrs 47 mins"
        },
        {
            "language": "CSS",
            "time": "60 hrs 42 mins"
        },
        {
            "language": "Dart",
            "time": "32 hrs 46 mins"
        },
        {
            "language": "Git Config",
            "time": "8 hrs 45 mins"
        },
        {
            "language": "GraphQL",
            "time": "8 hrs 23 mins"
        },
        {
            "language": "HTML",
            "time": "120 hrs 31 mins"
        },
        {
            "language": "JSON",
            "time": "177 hrs 52 mins"
        },
        {
            "language": "JavaScript",
            "time": "3,867 hrs 57 mins"
        },
        {
            "language": "Markdown",
            "time": "55 hrs 39 mins"
        },
        {
            "language": "Python",
            "time": "153 hrs 29 mins"
        },
        {
            "language": "SCSS",
            "time": "138 hrs 43 mins"
        },
        {
            "language": "SQL",
            "time": "18 hrs 57 mins"
        },
        {
            "language": "Svelte",
            "time": "15 hrs 49 mins"
        },
        {
            "language": "TSConfig",
            "time": "3 hrs 2 mins"
        },
        {
            "language": "Text",
            "time": "6 hrs 51 mins"
        },
        {
            "language": "TypeScript",
            "time": "280 hrs 22 mins"
        },
        {
            "language": "Vue.js",
            "time": "195 hrs 6 mins"
        },
        {
            "language": "XML",
            "time": "6 hrs 14 mins"
        }
    ]
}