{
    "total_time": "1,168 hrs 19 mins",
    "updated": true,
    "elo": 1169,
    "languages": [
        {
            "language": "Dart",
            "time": "1,137 hrs 17 mins"
        },
        {
            "language": "Gradle Kotlin DSL",
            "time": "3 hrs 56 mins"
        },
        {
            "language": "JSON",
            "time": "5 hrs 47 mins"
        },
        {
            "language": "TypeScript",
            "time": "3 hrs 24 mins"
        },
        {
            "language": "XML",
            "time": "8 hrs 19 mins"
        },
        {
            "language": "YAML",
            "time": "9 hrs 36 mins"
        }
    ]
}