{
    "total_time": "696 hrs 13 mins",
    "updated": true,
    "elo": 697,
    "languages": [
        {
            "language": "CSS",
            "time": "17 hrs 41 mins"
        },
        {
            "language": "JSON",
            "time": "27 hrs 47 mins"
        },
        {
            "language": "JavaScript",
            "time": "5 hrs 28 mins"
        },
        {
            "language": "Markdown",
            "time": "21 hrs"
        },
        {
            "language": "TypeScript",
            "time": "193 hrs 30 mins"
        },
        {
            "language": "Vue.js",
            "time": "430 hrs 47 mins"
        }
    ]
}