{
    "total_time": "1,298 hrs 53 mins",
    "updated": true,
    "elo": 1304,
    "languages": [
        {
            "language": "Bash",
            "time": "26 hrs 55 mins"
        },
        {
            "language": "CSS",
            "time": "5 hrs 37 mins"
        },
        {
            "language": "Docker",
            "time": "13 hrs 8 mins"
        },
        {
            "language": "JSON",
            "time": "66 hrs 9 mins"
        },
        {
            "language": "JavaScript",
            "time": "163 hrs 16 mins"
        },
        {
            "language": "Markdown",
            "time": "40 hrs 45 mins"
        },
        {
            "language": "TypeScript",
            "time": "451 hrs 48 mins"
        },
        {
            "language": "Vue.js",
            "time": "501 hrs 20 mins"
        },
        {
            "language": "YAML",
            "time": "29 hrs 55 mins"
        }
    ]
}