{
    "total_time": "1,087 hrs 2 mins",
    "updated": true,
    "elo": 1088,
    "languages": [
        {
            "language": "Bash",
            "time": "16 hrs 54 mins"
        },
        {
            "language": "CSS",
            "time": "10 hrs 13 mins"
        },
        {
            "language": "CocoaPods",
            "time": "7 hrs 1 min"
        },
        {
            "language": "Dart",
            "time": "189 hrs 11 mins"
        },
        {
            "language": "Git Config",
            "time": "2 hrs 38 mins"
        },
        {
            "language": "JSON",
            "time": "27 hrs 14 mins"
        },
        {
            "language": "JavaScript",
            "time": "9 hrs 18 mins"
        },
        {
            "language": "Markdown",
            "time": "42 hrs 31 mins"
        },
        {
            "language": "Prisma",
            "time": "15 hrs 44 mins"
        },
        {
            "language": "Python",
            "time": "12 hrs 5 mins"
        },
        {
            "language": "Swift",
            "time": "5 hrs 39 mins"
        },
        {
            "language": "Text",
            "time": "7 hrs 34 mins"
        },
        {
            "language": "TypeScript",
            "time": "725 hrs 33 mins"
        },
        {
            "language": "XML",
            "time": "3 hrs 45 mins"
        },
        {
            "language": "YAML",
            "time": "11 hrs 42 mins"
        }
    ]
}