{
    "total_time": "2,795 hrs 14 mins",
    "updated": true,
    "elo": 2796,
    "languages": [
        {
            "language": "Bash",
            "time": "6 hrs 7 mins"
        },
        {
            "language": "CSS",
            "time": "64 hrs 30 mins"
        },
        {
            "language": "HTML",
            "time": "41 hrs 6 mins"
        },
        {
            "language": "JSON",
            "time": "62 hrs 52 mins"
        },
        {
            "language": "JavaScript",
            "time": "745 hrs 34 mins"
        },
        {
            "language": "Markdown",
            "time": "75 hrs 25 mins"
        },
        {
            "language": "Python",
            "time": "2 hrs 58 mins"
        },
        {
            "language": "SCSS",
            "time": "5 hrs 7 mins"
        },
        {
            "language": "Text",
            "time": "4 hrs 38 mins"
        },
        {
            "language": "TypeScript",
            "time": "1,042 hrs 58 mins"
        },
        {
            "language": "Vue.js",
            "time": "741 hrs 20 mins"
        },
        {
            "language": "YAML",
            "time": "2 hrs 39 mins"
        }
    ]
}