{
    "total_time": "2,838 hrs 55 mins",
    "updated": true,
    "elo": 2839,
    "languages": [
        {
            "language": ".env file",
            "time": "10 hrs 47 mins"
        },
        {
            "language": "Bash",
            "time": "19 hrs 57 mins"
        },
        {
            "language": "Blade Template",
            "time": "472 hrs 52 mins"
        },
        {
            "language": "CSS",
            "time": "4 hrs 55 mins"
        },
        {
            "language": "HTML",
            "time": "87 hrs 41 mins"
        },
        {
            "language": "JSON",
            "time": "10 hrs 45 mins"
        },
        {
            "language": "JavaScript",
            "time": "39 hrs 43 mins"
        },
        {
            "language": "PHP",
            "time": "1,461 hrs 18 mins"
        },
        {
            "language": "Python",
            "time": "43 hrs 17 mins"
        },
        {
            "language": "SCSS",
            "time": "27 hrs 42 mins"
        },
        {
            "language": "SQL",
            "time": "4 hrs 34 mins"
        },
        {
            "language": "TypeScript",
            "time": "606 hrs 15 mins"
        },
        {
            "language": "YAML",
            "time": "2 hrs 50 mins"
        },
        {
            "language": "textmate",
            "time": "46 hrs 19 mins"
        }
    ]
}