{
    "total_time": "2,201 hrs 7 mins",
    "updated": true,
    "elo": 2320,
    "languages": [
        {
            "language": "CSS",
            "time": "3 hrs 57 mins"
        },
        {
            "language": "HTML",
            "time": "3 hrs"
        },
        {
            "language": "JSON",
            "time": "156 hrs 50 mins"
        },
        {
            "language": "JavaScript",
            "time": "71 hrs 52 mins"
        },
        {
            "language": "Markdown",
            "time": "58 hrs 8 mins"
        },
        {
            "language": "SCSS",
            "time": "23 hrs 24 mins"
        },
        {
            "language": "TSConfig",
            "time": "15 hrs 53 mins"
        },
        {
            "language": "TypeScript",
            "time": "1,211 hrs 45 mins"
        },
        {
            "language": "Vue.js",
            "time": "622 hrs 38 mins"
        },
        {
            "language": "XSLT",
            "time": "2 hrs 43 mins"
        },
        {
            "language": "YAML",
            "time": "30 hrs 57 mins"
        }
    ]
}