{
    "total_time": "471 hrs 11 mins",
    "updated": true,
    "elo": 472,
    "languages": [
        {
            "language": "Bash",
            "time": "64 hrs 29 mins"
        },
        {
            "language": "C",
            "time": "22 hrs 32 mins"
        },
        {
            "language": "C++",
            "time": "86 hrs 14 mins"
        },
        {
            "language": "CMake",
            "time": "7 hrs 2 mins"
        },
        {
            "language": "Dart",
            "time": "114 hrs 13 mins"
        },
        {
            "language": "GLSL",
            "time": "8 hrs 13 mins"
        },
        {
            "language": "GN",
            "time": "4 hrs 17 mins"
        },
        {
            "language": "Groovy",
            "time": "3 hrs 19 mins"
        },
        {
            "language": "JSON",
            "time": "11 hrs 28 mins"
        },
        {
            "language": "Java",
            "time": "2 hrs 43 mins"
        },
        {
            "language": "Makefile",
            "time": "6 hrs 17 mins"
        },
        {
            "language": "Markdown",
            "time": "119 hrs 3 mins"
        },
        {
            "language": "Swift",
            "time": "7 hrs 37 mins"
        },
        {
            "language": "Text",
            "time": "4 hrs 35 mins"
        },
        {
            "language": "YAML",
            "time": "9 hrs 9 mins"
        }
    ]
}