{
    "total_time": "1,324 hrs 40 mins",
    "updated": true,
    "elo": 1389,
    "languages": [
        {
            "language": "Bash",
            "time": "4 hrs 9 mins"
        },
        {
            "language": "CSS",
            "time": "46 hrs 20 mins"
        },
        {
            "language": "Go",
            "time": "185 hrs 25 mins"
        },
        {
            "language": "HTML",
            "time": "66 hrs 48 mins"
        },
        {
            "language": "Image (svg)",
            "time": "4 hrs 26 mins"
        },
        {
            "language": "JSON",
            "time": "37 hrs 37 mins"
        },
        {
            "language": "Java",
            "time": "40 hrs 31 mins"
        },
        {
            "language": "JavaScript",
            "time": "350 hrs 49 mins"
        },
        {
            "language": "Markdown",
            "time": "84 hrs 49 mins"
        },
        {
            "language": "PHP",
            "time": "7 hrs 27 mins"
        },
        {
            "language": "Python",
            "time": "2 hrs 59 mins"
        },
        {
            "language": "Rust",
            "time": "109 hrs 10 mins"
        },
        {
            "language": "SCSS",
            "time": "3 hrs 49 mins"
        },
        {
            "language": "Solidity",
            "time": "27 hrs 49 mins"
        },
        {
            "language": "Svelte",
            "time": "15 hrs 28 mins"
        },
        {
            "language": "TOML",
            "time": "3 hrs 43 mins"
        },
        {
            "language": "TSConfig",
            "time": "2 hrs 36 mins"
        },
        {
            "language": "Text",
            "time": "6 hrs 25 mins"
        },
        {
            "language": "TypeScript",
            "time": "315 hrs 6 mins"
        },
        {
            "language": "YAML",
            "time": "9 hrs 14 mins"
        }
    ]
}