{
    "total_time": "1,378 hrs 11 mins",
    "updated": true,
    "elo": 1416,
    "languages": [
        {
            "language": "Bash",
            "time": "25 hrs 56 mins"
        },
        {
            "language": "C",
            "time": "28 hrs 7 mins"
        },
        {
            "language": "C/C++",
            "time": "16 hrs 39 mins"
        },
        {
            "language": "CSS",
            "time": "3 hrs 36 mins"
        },
        {
            "language": "Docker",
            "time": "11 hrs 38 mins"
        },
        {
            "language": "Git Config",
            "time": "3 hrs 1 min"
        },
        {
            "language": "Go",
            "time": "232 hrs 14 mins"
        },
        {
            "language": "HTML",
            "time": "13 hrs 31 mins"
        },
        {
            "language": "JSON",
            "time": "92 hrs 8 mins"
        },
        {
            "language": "Java",
            "time": "73 hrs 22 mins"
        },
        {
            "language": "JavaScript",
            "time": "49 hrs 5 mins"
        },
        {
            "language": "Makefile",
            "time": "11 hrs 27 mins"
        },
        {
            "language": "Markdown",
            "time": "19 hrs 3 mins"
        },
        {
            "language": "Python",
            "time": "41 hrs 55 mins"
        },
        {
            "language": "SQL",
            "time": "28 hrs 51 mins"
        },
        {
            "language": "TSConfig",
            "time": "4 hrs 19 mins"
        },
        {
            "language": "Text",
            "time": "30 hrs 35 mins"
        },
        {
            "language": "TypeScript",
            "time": "670 hrs 4 mins"
        },
        {
            "language": "XML",
            "time": "5 hrs 53 mins"
        },
        {
            "language": "YAML",
            "time": "16 hrs 47 mins"
        }
    ]
}