{
    "total_time": "700 hrs 33 mins",
    "updated": true,
    "elo": 701,
    "languages": [
        {
            "language": "C",
            "time": "7 hrs 26 mins"
        },
        {
            "language": "C++",
            "time": "16 hrs 47 mins"
        },
        {
            "language": "CSV",
            "time": "8 hrs 56 mins"
        },
        {
            "language": "Git Config",
            "time": "7 hrs 34 mins"
        },
        {
            "language": "JSON",
            "time": "2 hrs 51 mins"
        },
        {
            "language": "MATLAB",
            "time": "38 hrs 17 mins"
        },
        {
            "language": "Markdown",
            "time": "7 hrs 36 mins"
        },
        {
            "language": "Python",
            "time": "559 hrs 46 mins"
        },
        {
            "language": "Text",
            "time": "41 hrs 18 mins"
        },
        {
            "language": "YAML",
            "time": "10 hrs 2 mins"
        }
    ]
}