{
    "total_time": "1,874 hrs 36 mins",
    "updated": true,
    "elo": 1875,
    "languages": [
        {
            "language": "Bash",
            "time": "7 hrs 51 mins"
        },
        {
            "language": "BibTeX",
            "time": "6 hrs 9 mins"
        },
        {
            "language": "C",
            "time": "145 hrs 23 mins"
        },
        {
            "language": "C#",
            "time": "147 hrs 22 mins"
        },
        {
            "language": "C++",
            "time": "27 hrs 9 mins"
        },
        {
            "language": "CMake",
            "time": "4 hrs 3 mins"
        },
        {
            "language": "CSV",
            "time": "5 hrs 9 mins"
        },
        {
            "language": "EJS",
            "time": "3 hrs 46 mins"
        },
        {
            "language": "Git Config",
            "time": "4 hrs 11 mins"
        },
        {
            "language": "Go",
            "time": "21 hrs 2 mins"
        },
        {
            "language": "HTML",
            "time": "16 hrs 1 min"
        },
        {
            "language": "JSON",
            "time": "35 hrs 3 mins"
        },
        {
            "language": "Java",
            "time": "10 hrs 13 mins"
        },
        {
            "language": "Java Properties",
            "time": "2 hrs 49 mins"
        },
        {
            "language": "JavaScript",
            "time": "33 hrs 49 mins"
        },
        {
            "language": "MATLAB",
            "time": "7 hrs 20 mins"
        },
        {
            "language": "Markdown",
            "time": "331 hrs 8 mins"
        },
        {
            "language": "Perl",
            "time": "20 hrs 35 mins"
        },
        {
            "language": "Prolog",
            "time": "4 hrs 51 mins"
        },
        {
            "language": "Python",
            "time": "474 hrs 7 mins"
        },
        {
            "language": "SCSS",
            "time": "3 hrs 1 min"
        },
        {
            "language": "SQL",
            "time": "6 hrs 38 mins"
        },
        {
            "language": "Standard ML",
            "time": "4 hrs 2 mins"
        },
        {
            "language": "TeX",
            "time": "153 hrs 49 mins"
        },
        {
            "language": "Text",
            "time": "23 hrs 50 mins"
        },
        {
            "language": "TypeScript",
            "time": "329 hrs 9 mins"
        },
        {
            "language": "Typst",
            "time": "6 hrs 53 mins"
        },
        {
            "language": "Vue.js",
            "time": "19 hrs 38 mins"
        },
        {
            "language": "XML",
            "time": "11 hrs 26 mins"
        },
        {
            "language": "YAML",
            "time": "8 hrs 9 mins"
        }
    ]
}