{
    "total_time": "3,861 hrs 20 mins",
    "updated": true,
    "elo": 3862,
    "languages": [
        {
            "language": "Bash",
            "time": "12 hrs 56 mins"
        },
        {
            "language": "C++",
            "time": "7 hrs 10 mins"
        },
        {
            "language": "CSS",
            "time": "100 hrs 34 mins"
        },
        {
            "language": "Dart",
            "time": "2,341 hrs 31 mins"
        },
        {
            "language": "Git Config",
            "time": "3 hrs 50 mins"
        },
        {
            "language": "Groovy",
            "time": "28 hrs 3 mins"
        },
        {
            "language": "HTML",
            "time": "17 hrs 14 mins"
        },
        {
            "language": "JSON",
            "time": "52 hrs 23 mins"
        },
        {
            "language": "Java Properties",
            "time": "7 hrs 38 mins"
        },
        {
            "language": "JavaScript",
            "time": "806 hrs 48 mins"
        },
        {
            "language": "Kotlin",
            "time": "12 hrs 45 mins"
        },
        {
            "language": "Markdown",
            "time": "17 hrs 52 mins"
        },
        {
            "language": "Prisma",
            "time": "5 hrs 50 mins"
        },
        {
            "language": "Python",
            "time": "53 hrs 17 mins"
        },
        {
            "language": "Text",
            "time": "10 hrs 3 mins"
        },
        {
            "language": "TypeScript",
            "time": "325 hrs 44 mins"
        },
        {
            "language": "XML",
            "time": "15 hrs 26 mins"
        },
        {
            "language": "YAML",
            "time": "42 hrs 16 mins"
        }
    ]
}