{
    "total_time": "56 hrs 27 mins",
    "updated": true,
    "elo": 65,
    "languages": [
        {
            "language": "CSV",
            "time": "2 hrs 33 mins"
        },
        {
            "language": "JavaScript",
            "time": "9 hrs 13 mins"
        },
        {
            "language": "Markdown",
            "time": "2 hrs 37 mins"
        },
        {
            "language": "Python",
            "time": "9 hrs 35 mins"
        },
        {
            "language": "SQL",
            "time": "7 hrs 33 mins"
        },
        {
            "language": "TypeScript",
            "time": "16 hrs 3 mins"
        },
        {
            "language": "sh",
            "time": "8 hrs 53 mins"
        }
    ]
}