{
    "total_time": "48 hrs 5 mins",
    "updated": true,
    "elo": 57,
    "languages": [
        {
            "language": "JavaScript",
            "time": "5 hrs 8 mins"
        },
        {
            "language": "Python",
            "time": "17 hrs 56 mins"
        },
        {
            "language": "SQL",
            "time": "7 hrs 33 mins"
        },
        {
            "language": "TypeScript",
            "time": "7 hrs 46 mins"
        },
        {
            "language": "sh",
            "time": "9 hrs 42 mins"
        }
    ]
}