{
    "total_time": "4,530 hrs 17 mins",
    "updated": true,
    "elo": 4531,
    "languages": [
        {
            "language": ".env file",
            "time": "9 hrs 11 mins"
        },
        {
            "language": "Assembly",
            "time": "7 hrs 46 mins"
        },
        {
            "language": "Bash",
            "time": "55 hrs 18 mins"
        },
        {
            "language": "BibTeX",
            "time": "11 hrs 45 mins"
        },
        {
            "language": "C++",
            "time": "7 hrs 40 mins"
        },
        {
            "language": "CLASS",
            "time": "5 hrs 38 mins"
        },
        {
            "language": "CSS",
            "time": "4 hrs"
        },
        {
            "language": "CSV",
            "time": "2 hrs 42 mins"
        },
        {
            "language": "Docker",
            "time": "22 hrs 48 mins"
        },
        {
            "language": "Dockerfile",
            "time": "7 hrs 8 mins"
        },
        {
            "language": "Git Config",
            "time": "5 hrs 45 mins"
        },
        {
            "language": "HTML",
            "time": "8 hrs 22 mins"
        },
        {
            "language": "INI",
            "time": "3 hrs 48 mins"
        },
        {
            "language": "JSON",
            "time": "33 hrs 32 mins"
        },
        {
            "language": "Java",
            "time": "703 hrs 28 mins"
        },
        {
            "language": "JavaScript",
            "time": "61 hrs 52 mins"
        },
        {
            "language": "Markdown",
            "time": "41 hrs 32 mins"
        },
        {
            "language": "Python",
            "time": "1,918 hrs 42 mins"
        },
        {
            "language": "SSH Config",
            "time": "4 hrs 53 mins"
        },
        {
            "language": "Shell Script",
            "time": "11 hrs 45 mins"
        },
        {
            "language": "TeX",
            "time": "1,090 hrs 47 mins"
        },
        {
            "language": "Terraform",
            "time": "3 hrs 47 mins"
        },
        {
            "language": "Text",
            "time": "18 hrs 59 mins"
        },
        {
            "language": "TypeScript",
            "time": "19 hrs 27 mins"
        },
        {
            "language": "Vue.js",
            "time": "159 hrs 15 mins"
        },
        {
            "language": "XML",
            "time": "53 hrs 52 mins"
        },
        {
            "language": "YAML",
            "time": "252 hrs 57 mins"
        },
        {
            "language": "textmate",
            "time": "3 hrs 38 mins"
        }
    ]
}