{
    "total_time": "3,115 hrs 21 mins",
    "languages": [
        {
            "language": "C",
            "time": "468 hrs 8 mins"
        },
        {
            "language": "C++",
            "time": "141 hrs 8 mins"
        },
        {
            "language": "CSS",
            "time": "45 hrs 14 mins"
        },
        {
            "language": "Image (svg)",
            "time": "72 hrs 1 min"
        },
        {
            "language": "JSON",
            "time": "108 hrs 34 mins"
        },
        {
            "language": "Java",
            "time": "92 hrs 4 mins"
        },
        {
            "language": "JavaScript",
            "time": "367 hrs 38 mins"
        },
        {
            "language": "Other",
            "time": "183 hrs 9 mins"
        },
        {
            "language": "PHP",
            "time": "44 hrs 22 mins"
        },
        {
            "language": "Python",
            "time": "161 hrs 21 mins"
        },
        {
            "language": "SCSS",
            "time": "171 hrs 10 mins"
        },
        {
            "language": "SQL",
            "time": "109 hrs 42 mins"
        },
        {
            "language": "TypeScript",
            "time": "1,105 hrs 56 mins"
        },
        {
            "language": "YAML",
            "time": "44 hrs 54 mins"
        }
    ]
}